merkle_tree_stream/__init__.py
merkle_tree_stream/node.py
merkle_tree_stream/tree.py
merkle_tree_stream-0.0.1a5.dist-info/LICENSE
merkle_tree_stream-0.0.1a5.dist-info/WHEEL
merkle_tree_stream-0.0.1a5.dist-info/METADATA
merkle_tree_stream-0.0.1a5.dist-info/RECORD
