Metadata-Version: 2.1
Name: merkle-tree-stream
Version: 0.0.1a5
Summary: A stream that generates a merkle tree based on the incoming data
Home-page: https://github.com/hyperpy/merkle-tree-stream
Keywords: hypercore,hypercore-protocol
Author: decentral1se
Author-email: hi@decentral1.se
Maintainer: decentral1se
Maintainer-email: hi@decentral1.se
Requires-Python: >=3.6,<4.0
Classifier: Programming Language :: Python :: 3
Classifier: Programming Language :: Python :: 3.6
Classifier: Programming Language :: Python :: 3.7
Classifier: Programming Language :: Python :: 3.8
Requires-Dist: attrs (>=19.3.0,<20.0.0)
Requires-Dist: flat-tree (>=0.0.1-alpha.8,<0.0.2)
Project-URL: Repository, https://github.com/hyperpy/merkle-tree-stream
